{
    "os": "Linux-5.4.0-164-generic-x86_64-with-glibc2.35",
    "python": "3.10.0",
    "heartbeatAt": "2024-05-31T17:15:36.376370",
    "startedAt": "2024-05-31T17:15:35.692068",
    "docker": null,
    "cuda": null,
    "args": [],
    "state": "running",
    "program": "<python with no main file>",
    "codePathLocal": null,
    "git": {
        "remote": "https://github.com/fhswf/Slim",
        "commit": "19b42b76100cccb5f1a5dbb55f4dfd967619f074"
    },
    "email": "thomas_schmitt@gmx.de",
    "root": "/home/thsch026/masterarbeit/Slim",
    "host": "jupyter-thsch026",
    "username": "jovyan",
    "executable": "/home/thsch026/my-envs/kdein/bin/python",
    "cpu_count": 64,
    "cpu_count_logical": 128,
    "cpu_freq": {
        "current": 1713.0710937499991,
        "min": 1500.0,
        "max": 2400.0
    },
    "cpu_freq_per_core": [
        {
            "current": 1900.917,
            "min": 1500.0,
            "max": 2400.0
        },
        {
            "current": 1497.859,
            "min": 1500.0,
            "max": 2400.0
        },
        {
            "current": 1497.105,
            "min": 1500.0,
            "max": 2400.0
        },
        {
            "current": 1497.855,
            "min": 1500.0,
            "max": 2400.0
        },
        {
            "current": 1499.932,
            "min": 1500.0,
            "max": 2400.0
        },
        {
            "current": 1498.948,
            "min": 1500.0,
            "max": 2400.0
        },
        {
            "current": 1648.858,
            "min": 1500.0,
            "max": 2400.0
        },
        {
            "current": 3259.881,
            "min": 1500.0,
            "max": 2400.0
        },
        {
            "current": 1497.195,
            "min": 1500.0,
            "max": 2400.0
        },
        {
            "current": 1498.663,
            "min": 1500.0,
            "max": 2400.0
        },
        {
            "current": 1860.302,
            "min": 1500.0,
            "max": 2400.0
        },
        {
            "current": 1479.439,
            "min": 1500.0,
            "max": 2400.0
        },
        {
            "current": 1498.067,
            "min": 1500.0,
            "max": 2400.0
        },
        {
            "current": 1796.266,
            "min": 1500.0,
            "max": 2400.0
        },
        {
            "current": 1757.927,
            "min": 1500.0,
            "max": 2400.0
        },
        {
            "current": 1385.697,
            "min": 1500.0,
            "max": 2400.0
        },
        {
            "current": 1496.455,
            "min": 1500.0,
            "max": 2400.0
        },
        {
            "current": 1398.944,
            "min": 1500.0,
            "max": 2400.0
        },
        {
            "current": 1371.58,
            "min": 1500.0,
            "max": 2400.0
        },
        {
            "current": 1495.599,
            "min": 1500.0,
            "max": 2400.0
        },
        {
            "current": 1371.76,
            "min": 1500.0,
            "max": 2400.0
        },
        {
            "current": 1366.032,
            "min": 1500.0,
            "max": 2400.0
        },
        {
            "current": 1370.489,
            "min": 1500.0,
            "max": 2400.0
        },
        {
            "current": 1461.283,
            "min": 1500.0,
            "max": 2400.0
        },
        {
            "current": 1454.023,
            "min": 1500.0,
            "max": 2400.0
        },
        {
            "current": 1497.016,
            "min": 1500.0,
            "max": 2400.0
        },
        {
            "current": 1499.189,
            "min": 1500.0,
            "max": 2400.0
        },
        {
            "current": 1497.643,
            "min": 1500.0,
            "max": 2400.0
        },
        {
            "current": 1498.574,
            "min": 1500.0,
            "max": 2400.0
        },
        {
            "current": 1798.028,
            "min": 1500.0,
            "max": 2400.0
        },
        {
            "current": 1710.63,
            "min": 1500.0,
            "max": 2400.0
        },
        {
            "current": 2014.014,
            "min": 1500.0,
            "max": 2400.0
        },
        {
            "current": 1498.258,
            "min": 1500.0,
            "max": 2400.0
        },
        {
            "current": 1796.653,
            "min": 1500.0,
            "max": 2400.0
        },
        {
            "current": 1797.304,
            "min": 1500.0,
            "max": 2400.0
        },
        {
            "current": 1498.782,
            "min": 1500.0,
            "max": 2400.0
        },
        {
            "current": 1797.267,
            "min": 1500.0,
            "max": 2400.0
        },
        {
            "current": 1798.356,
            "min": 1500.0,
            "max": 2400.0
        },
        {
            "current": 1798.512,
            "min": 1500.0,
            "max": 2400.0
        },
        {
            "current": 1499.755,
            "min": 1500.0,
            "max": 2400.0
        },
        {
            "current": 1801.503,
            "min": 1500.0,
            "max": 2400.0
        },
        {
            "current": 1799.495,
            "min": 1500.0,
            "max": 2400.0
        },
        {
            "current": 2502.22,
            "min": 1500.0,
            "max": 2400.0
        },
        {
            "current": 1405.838,
            "min": 1500.0,
            "max": 2400.0
        },
        {
            "current": 1795.68,
            "min": 1500.0,
            "max": 2400.0
        },
        {
            "current": 1799.611,
            "min": 1500.0,
            "max": 2400.0
        },
        {
            "current": 2054.875,
            "min": 1500.0,
            "max": 2400.0
        },
        {
            "current": 3299.778,
            "min": 1500.0,
            "max": 2400.0
        },
        {
            "current": 1497.264,
            "min": 1500.0,
            "max": 2400.0
        },
        {
            "current": 1499.568,
            "min": 1500.0,
            "max": 2400.0
        },
        {
            "current": 1671.947,
            "min": 1500.0,
            "max": 2400.0
        },
        {
            "current": 3307.86,
            "min": 1500.0,
            "max": 2400.0
        },
        {
            "current": 1498.696,
            "min": 1500.0,
            "max": 2400.0
        },
        {
            "current": 1499.557,
            "min": 1500.0,
            "max": 2400.0
        },
        {
            "current": 1497.498,
            "min": 1500.0,
            "max": 2400.0
        },
        {
            "current": 1500.055,
            "min": 1500.0,
            "max": 2400.0
        },
        {
            "current": 1495.307,
            "min": 1500.0,
            "max": 2400.0
        },
        {
            "current": 1797.254,
            "min": 1500.0,
            "max": 2400.0
        },
        {
            "current": 1798.118,
            "min": 1500.0,
            "max": 2400.0
        },
        {
            "current": 1797.758,
            "min": 1500.0,
            "max": 2400.0
        },
        {
            "current": 1800.408,
            "min": 1500.0,
            "max": 2400.0
        },
        {
            "current": 1795.856,
            "min": 1500.0,
            "max": 2400.0
        },
        {
            "current": 1796.729,
            "min": 1500.0,
            "max": 2400.0
        },
        {
            "current": 1498.951,
            "min": 1500.0,
            "max": 2400.0
        },
        {
            "current": 3288.017,
            "min": 1500.0,
            "max": 2400.0
        },
        {
            "current": 1465.434,
            "min": 1500.0,
            "max": 2400.0
        },
        {
            "current": 1498.868,
            "min": 1500.0,
            "max": 2400.0
        },
        {
            "current": 1499.36,
            "min": 1500.0,
            "max": 2400.0
        },
        {
            "current": 1499.434,
            "min": 1500.0,
            "max": 2400.0
        },
        {
            "current": 1501.097,
            "min": 1500.0,
            "max": 2400.0
        },
        {
            "current": 2133.717,
            "min": 1500.0,
            "max": 2400.0
        },
        {
            "current": 3295.445,
            "min": 1500.0,
            "max": 2400.0
        },
        {
            "current": 1498.018,
            "min": 1500.0,
            "max": 2400.0
        },
        {
            "current": 1498.117,
            "min": 1500.0,
            "max": 2400.0
        },
        {
            "current": 2260.907,
            "min": 1500.0,
            "max": 2400.0
        },
        {
            "current": 1498.595,
            "min": 1500.0,
            "max": 2400.0
        },
        {
            "current": 1485.423,
            "min": 1500.0,
            "max": 2400.0
        },
        {
            "current": 2264.286,
            "min": 1500.0,
            "max": 2400.0
        },
        {
            "current": 1499.697,
            "min": 1500.0,
            "max": 2400.0
        },
        {
            "current": 1397.762,
            "min": 1500.0,
            "max": 2400.0
        },
        {
            "current": 1464.713,
            "min": 1500.0,
            "max": 2400.0
        },
        {
            "current": 1458.968,
            "min": 1500.0,
            "max": 2400.0
        },
        {
            "current": 1401.645,
            "min": 1500.0,
            "max": 2400.0
        },
        {
            "current": 1393.378,
            "min": 1500.0,
            "max": 2400.0
        },
        {
            "current": 1404.692,
            "min": 1500.0,
            "max": 2400.0
        },
        {
            "current": 1495.69,
            "min": 1500.0,
            "max": 2400.0
        },
        {
            "current": 1496.425,
            "min": 1500.0,
            "max": 2400.0
        },
        {
            "current": 1497.076,
            "min": 1500.0,
            "max": 2400.0
        },
        {
            "current": 1496.722,
            "min": 1500.0,
            "max": 2400.0
        },
        {
            "current": 1499.013,
            "min": 1500.0,
            "max": 2400.0
        },
        {
            "current": 1498.736,
            "min": 1500.0,
            "max": 2400.0
        },
        {
            "current": 1496.524,
            "min": 1500.0,
            "max": 2400.0
        },
        {
            "current": 1500.637,
            "min": 1500.0,
            "max": 2400.0
        },
        {
            "current": 1799.711,
            "min": 1500.0,
            "max": 2400.0
        },
        {
            "current": 1646.911,
            "min": 1500.0,
            "max": 2400.0
        },
        {
            "current": 3297.719,
            "min": 1500.0,
            "max": 2400.0
        },
        {
            "current": 1404.609,
            "min": 1500.0,
            "max": 2400.0
        },
        {
            "current": 1661.678,
            "min": 1500.0,
            "max": 2400.0
        },
        {
            "current": 1657.843,
            "min": 1500.0,
            "max": 2400.0
        },
        {
            "current": 1492.063,
            "min": 1500.0,
            "max": 2400.0
        },
        {
            "current": 1657.145,
            "min": 1500.0,
            "max": 2400.0
        },
        {
            "current": 1654.835,
            "min": 1500.0,
            "max": 2400.0
        },
        {
            "current": 1658.613,
            "min": 1500.0,
            "max": 2400.0
        },
        {
            "current": 1445.485,
            "min": 1500.0,
            "max": 2400.0
        },
        {
            "current": 2107.301,
            "min": 1500.0,
            "max": 2400.0
        },
        {
            "current": 2065.112,
            "min": 1500.0,
            "max": 2400.0
        },
        {
            "current": 2266.458,
            "min": 1500.0,
            "max": 2400.0
        },
        {
            "current": 1164.191,
            "min": 1500.0,
            "max": 2400.0
        },
        {
            "current": 2304.993,
            "min": 1500.0,
            "max": 2400.0
        },
        {
            "current": 2267.686,
            "min": 1500.0,
            "max": 2400.0
        },
        {
            "current": 2652.228,
            "min": 1500.0,
            "max": 2400.0
        },
        {
            "current": 3296.961,
            "min": 1500.0,
            "max": 2400.0
        },
        {
            "current": 1500.244,
            "min": 1500.0,
            "max": 2400.0
        },
        {
            "current": 1499.143,
            "min": 1500.0,
            "max": 2400.0
        },
        {
            "current": 1615.514,
            "min": 1500.0,
            "max": 2400.0
        },
        {
            "current": 3300.2,
            "min": 1500.0,
            "max": 2400.0
        },
        {
            "current": 1497.807,
            "min": 1500.0,
            "max": 2400.0
        },
        {
            "current": 1496.066,
            "min": 1500.0,
            "max": 2400.0
        },
        {
            "current": 1499.322,
            "min": 1500.0,
            "max": 2400.0
        },
        {
            "current": 1499.592,
            "min": 1500.0,
            "max": 2400.0
        },
        {
            "current": 1495.764,
            "min": 1500.0,
            "max": 2400.0
        },
        {
            "current": 1794.866,
            "min": 1500.0,
            "max": 2400.0
        },
        {
            "current": 1800.388,
            "min": 1500.0,
            "max": 2400.0
        },
        {
            "current": 1797.46,
            "min": 1500.0,
            "max": 2400.0
        },
        {
            "current": 1798.045,
            "min": 1500.0,
            "max": 2400.0
        },
        {
            "current": 1796.546,
            "min": 1500.0,
            "max": 2400.0
        },
        {
            "current": 1795.269,
            "min": 1500.0,
            "max": 2400.0
        },
        {
            "current": 1498.338,
            "min": 1500.0,
            "max": 2400.0
        }
    ],
    "disk": {
        "/": {
            "total": 3638.31258392334,
            "used": 1109.0996170043945
        }
    },
    "gpu": "NVIDIA A100-SXM4-80GB",
    "gpu_count": 4,
    "gpu_devices": [
        {
            "name": "NVIDIA A100-SXM4-80GB",
            "memory_total": 85899345920
        },
        {
            "name": "NVIDIA A100-SXM4-80GB",
            "memory_total": 85899345920
        },
        {
            "name": "NVIDIA A100-SXM4-80GB",
            "memory_total": 85899345920
        },
        {
            "name": "NVIDIA A100-SXM4-80GB",
            "memory_total": 85899345920
        }
    ],
    "memory": {
        "total": 503.78936767578125
    }
}
