{
    "os": "Linux-5.4.0-164-generic-x86_64-with-glibc2.35",
    "python": "3.10.0",
    "heartbeatAt": "2024-06-19T15:29:48.208947",
    "startedAt": "2024-06-19T15:29:47.308223",
    "docker": null,
    "cuda": null,
    "args": [],
    "state": "running",
    "program": "<python with no main file>",
    "codePathLocal": null,
    "git": {
        "remote": "https://github.com/fhswf/Slim",
        "commit": "19b42b76100cccb5f1a5dbb55f4dfd967619f074"
    },
    "email": "thomas_schmitt@gmx.de",
    "root": "/home/thsch026/masterarbeit/Slim",
    "host": "jupyter-thsch026",
    "username": "jovyan",
    "executable": "/home/thsch026/my-envs/kdein/bin/python",
    "cpu_count": 64,
    "cpu_count_logical": 128,
    "cpu_freq": {
        "current": 1753.4930390625,
        "min": 1500.0,
        "max": 2400.0
    },
    "cpu_freq_per_core": [
        {
            "current": 1400.544,
            "min": 1500.0,
            "max": 2400.0
        },
        {
            "current": 1485.435,
            "min": 1500.0,
            "max": 2400.0
        },
        {
            "current": 3299.776,
            "min": 1500.0,
            "max": 2400.0
        },
        {
            "current": 1573.046,
            "min": 1500.0,
            "max": 2400.0
        },
        {
            "current": 1849.475,
            "min": 1500.0,
            "max": 2400.0
        },
        {
            "current": 1422.583,
            "min": 1500.0,
            "max": 2400.0
        },
        {
            "current": 1756.697,
            "min": 1500.0,
            "max": 2400.0
        },
        {
            "current": 1480.264,
            "min": 1500.0,
            "max": 2400.0
        },
        {
            "current": 3303.776,
            "min": 1500.0,
            "max": 2400.0
        },
        {
            "current": 3302.344,
            "min": 1500.0,
            "max": 2400.0
        },
        {
            "current": 3276.611,
            "min": 1500.0,
            "max": 2400.0
        },
        {
            "current": 3294.409,
            "min": 1500.0,
            "max": 2400.0
        },
        {
            "current": 1464.37,
            "min": 1500.0,
            "max": 2400.0
        },
        {
            "current": 3278.012,
            "min": 1500.0,
            "max": 2400.0
        },
        {
            "current": 1497.979,
            "min": 1500.0,
            "max": 2400.0
        },
        {
            "current": 1499.38,
            "min": 1500.0,
            "max": 2400.0
        },
        {
            "current": 2962.727,
            "min": 1500.0,
            "max": 2400.0
        },
        {
            "current": 1675.725,
            "min": 1500.0,
            "max": 2400.0
        },
        {
            "current": 3074.675,
            "min": 1500.0,
            "max": 2400.0
        },
        {
            "current": 1711.15,
            "min": 1500.0,
            "max": 2400.0
        },
        {
            "current": 1796.996,
            "min": 1500.0,
            "max": 2400.0
        },
        {
            "current": 1494.92,
            "min": 1500.0,
            "max": 2400.0
        },
        {
            "current": 1625.984,
            "min": 1500.0,
            "max": 2400.0
        },
        {
            "current": 3300.431,
            "min": 1500.0,
            "max": 2400.0
        },
        {
            "current": 1399.043,
            "min": 1500.0,
            "max": 2400.0
        },
        {
            "current": 1713.054,
            "min": 1500.0,
            "max": 2400.0
        },
        {
            "current": 3290.178,
            "min": 1500.0,
            "max": 2400.0
        },
        {
            "current": 3302.083,
            "min": 1500.0,
            "max": 2400.0
        },
        {
            "current": 3301.58,
            "min": 1500.0,
            "max": 2400.0
        },
        {
            "current": 3289.505,
            "min": 1500.0,
            "max": 2400.0
        },
        {
            "current": 3284.714,
            "min": 1500.0,
            "max": 2400.0
        },
        {
            "current": 1882.24,
            "min": 1500.0,
            "max": 2400.0
        },
        {
            "current": 3293.245,
            "min": 1500.0,
            "max": 2400.0
        },
        {
            "current": 3289.173,
            "min": 1500.0,
            "max": 2400.0
        },
        {
            "current": 3290.781,
            "min": 1500.0,
            "max": 2400.0
        },
        {
            "current": 3301.767,
            "min": 1500.0,
            "max": 2400.0
        },
        {
            "current": 3304.044,
            "min": 1500.0,
            "max": 2400.0
        },
        {
            "current": 3288.845,
            "min": 1500.0,
            "max": 2400.0
        },
        {
            "current": 3297.834,
            "min": 1500.0,
            "max": 2400.0
        },
        {
            "current": 2894.063,
            "min": 1500.0,
            "max": 2400.0
        },
        {
            "current": 3268.676,
            "min": 1500.0,
            "max": 2400.0
        },
        {
            "current": 2443.242,
            "min": 1500.0,
            "max": 2400.0
        },
        {
            "current": 2833.847,
            "min": 1500.0,
            "max": 2400.0
        },
        {
            "current": 3300.122,
            "min": 1500.0,
            "max": 2400.0
        },
        {
            "current": 3299.903,
            "min": 1500.0,
            "max": 2400.0
        },
        {
            "current": 3285.996,
            "min": 1500.0,
            "max": 2400.0
        },
        {
            "current": 3300.108,
            "min": 1500.0,
            "max": 2400.0
        },
        {
            "current": 3301.258,
            "min": 1500.0,
            "max": 2400.0
        },
        {
            "current": 3053.499,
            "min": 1500.0,
            "max": 2400.0
        },
        {
            "current": 3299.81,
            "min": 1500.0,
            "max": 2400.0
        },
        {
            "current": 1889.789,
            "min": 1500.0,
            "max": 2400.0
        },
        {
            "current": 3002.342,
            "min": 1500.0,
            "max": 2400.0
        },
        {
            "current": 3260.182,
            "min": 1500.0,
            "max": 2400.0
        },
        {
            "current": 3273.338,
            "min": 1500.0,
            "max": 2400.0
        },
        {
            "current": 3304.441,
            "min": 1500.0,
            "max": 2400.0
        },
        {
            "current": 1463.718,
            "min": 1500.0,
            "max": 2400.0
        },
        {
            "current": 3300.122,
            "min": 1500.0,
            "max": 2400.0
        },
        {
            "current": 3309.363,
            "min": 1500.0,
            "max": 2400.0
        },
        {
            "current": 1890.571,
            "min": 1500.0,
            "max": 2400.0
        },
        {
            "current": 3299.94,
            "min": 1500.0,
            "max": 2400.0
        },
        {
            "current": 2114.337,
            "min": 1500.0,
            "max": 2400.0
        },
        {
            "current": 3295.138,
            "min": 1500.0,
            "max": 2400.0
        },
        {
            "current": 3067.846,
            "min": 1500.0,
            "max": 2400.0
        },
        {
            "current": 3306.102,
            "min": 1500.0,
            "max": 2400.0
        },
        {
            "current": 1497.827,
            "min": 1500.0,
            "max": 2400.0
        },
        {
            "current": 1366.656,
            "min": 1500.0,
            "max": 2400.0
        },
        {
            "current": 2926.407,
            "min": 1500.0,
            "max": 2400.0
        },
        {
            "current": 2731.391,
            "min": 1500.0,
            "max": 2400.0
        },
        {
            "current": 1773.17,
            "min": 1500.0,
            "max": 2400.0
        },
        {
            "current": 1331.184,
            "min": 1500.0,
            "max": 2400.0
        },
        {
            "current": 1657.109,
            "min": 1500.0,
            "max": 2400.0
        },
        {
            "current": 1428.414,
            "min": 1500.0,
            "max": 2400.0
        },
        {
            "current": 2721.618,
            "min": 1500.0,
            "max": 2400.0
        },
        {
            "current": 3295.037,
            "min": 1500.0,
            "max": 2400.0
        },
        {
            "current": 2524.848,
            "min": 1500.0,
            "max": 2400.0
        },
        {
            "current": 3304.76,
            "min": 1500.0,
            "max": 2400.0
        },
        {
            "current": 1440.971,
            "min": 1500.0,
            "max": 2400.0
        },
        {
            "current": 3296.31,
            "min": 1500.0,
            "max": 2400.0
        },
        {
            "current": 1399.045,
            "min": 1500.0,
            "max": 2400.0
        },
        {
            "current": 1405.208,
            "min": 1500.0,
            "max": 2400.0
        },
        {
            "current": 3309.033,
            "min": 1500.0,
            "max": 2400.0
        },
        {
            "current": 1837.427,
            "min": 1500.0,
            "max": 2400.0
        },
        {
            "current": 3301.109,
            "min": 1500.0,
            "max": 2400.0
        },
        {
            "current": 1650.061,
            "min": 1500.0,
            "max": 2400.0
        },
        {
            "current": 2275.394,
            "min": 1500.0,
            "max": 2400.0
        },
        {
            "current": 1436.429,
            "min": 1500.0,
            "max": 2400.0
        },
        {
            "current": 1587.8,
            "min": 1500.0,
            "max": 2400.0
        },
        {
            "current": 3296.355,
            "min": 1500.0,
            "max": 2400.0
        },
        {
            "current": 1498.752,
            "min": 1500.0,
            "max": 2400.0
        },
        {
            "current": 1684.668,
            "min": 1500.0,
            "max": 2400.0
        },
        {
            "current": 3292.506,
            "min": 1500.0,
            "max": 2400.0
        },
        {
            "current": 2943.334,
            "min": 1500.0,
            "max": 2400.0
        },
        {
            "current": 2916.275,
            "min": 1500.0,
            "max": 2400.0
        },
        {
            "current": 3301.068,
            "min": 1500.0,
            "max": 2400.0
        },
        {
            "current": 3272.852,
            "min": 1500.0,
            "max": 2400.0
        },
        {
            "current": 1882.757,
            "min": 1500.0,
            "max": 2400.0
        },
        {
            "current": 3299.918,
            "min": 1500.0,
            "max": 2400.0
        },
        {
            "current": 3293.003,
            "min": 1500.0,
            "max": 2400.0
        },
        {
            "current": 3299.234,
            "min": 1500.0,
            "max": 2400.0
        },
        {
            "current": 3302.997,
            "min": 1500.0,
            "max": 2400.0
        },
        {
            "current": 3295.745,
            "min": 1500.0,
            "max": 2400.0
        },
        {
            "current": 3299.346,
            "min": 1500.0,
            "max": 2400.0
        },
        {
            "current": 3294.69,
            "min": 1500.0,
            "max": 2400.0
        },
        {
            "current": 1506.936,
            "min": 1500.0,
            "max": 2400.0
        },
        {
            "current": 2388.832,
            "min": 1500.0,
            "max": 2400.0
        },
        {
            "current": 1916.221,
            "min": 1500.0,
            "max": 2400.0
        },
        {
            "current": 2509.109,
            "min": 1500.0,
            "max": 2400.0
        },
        {
            "current": 3300.403,
            "min": 1500.0,
            "max": 2400.0
        },
        {
            "current": 3295.319,
            "min": 1500.0,
            "max": 2400.0
        },
        {
            "current": 1493.643,
            "min": 1500.0,
            "max": 2400.0
        },
        {
            "current": 2392.299,
            "min": 1500.0,
            "max": 2400.0
        },
        {
            "current": 2591.646,
            "min": 1500.0,
            "max": 2400.0
        },
        {
            "current": 1907.565,
            "min": 1500.0,
            "max": 2400.0
        },
        {
            "current": 3303.274,
            "min": 1500.0,
            "max": 2400.0
        },
        {
            "current": 1920.51,
            "min": 1500.0,
            "max": 2400.0
        },
        {
            "current": 2605.87,
            "min": 1500.0,
            "max": 2400.0
        },
        {
            "current": 3297.475,
            "min": 1500.0,
            "max": 2400.0
        },
        {
            "current": 3298.928,
            "min": 1500.0,
            "max": 2400.0
        },
        {
            "current": 3310.546,
            "min": 1500.0,
            "max": 2400.0
        },
        {
            "current": 1432.71,
            "min": 1500.0,
            "max": 2400.0
        },
        {
            "current": 3294.484,
            "min": 1500.0,
            "max": 2400.0
        },
        {
            "current": 3299.816,
            "min": 1500.0,
            "max": 2400.0
        },
        {
            "current": 1805.292,
            "min": 1500.0,
            "max": 2400.0
        },
        {
            "current": 3289.375,
            "min": 1500.0,
            "max": 2400.0
        },
        {
            "current": 2202.528,
            "min": 1500.0,
            "max": 2400.0
        },
        {
            "current": 3298.935,
            "min": 1500.0,
            "max": 2400.0
        },
        {
            "current": 1411.462,
            "min": 1500.0,
            "max": 2400.0
        },
        {
            "current": 3292.383,
            "min": 1500.0,
            "max": 2400.0
        }
    ],
    "disk": {
        "/": {
            "total": 3638.31258392334,
            "used": 1109.280143737793
        }
    },
    "gpu": "NVIDIA A100-SXM4-80GB",
    "gpu_count": 4,
    "gpu_devices": [
        {
            "name": "NVIDIA A100-SXM4-80GB",
            "memory_total": 85899345920
        },
        {
            "name": "NVIDIA A100-SXM4-80GB",
            "memory_total": 85899345920
        },
        {
            "name": "NVIDIA A100-SXM4-80GB",
            "memory_total": 85899345920
        },
        {
            "name": "NVIDIA A100-SXM4-80GB",
            "memory_total": 85899345920
        }
    ],
    "memory": {
        "total": 503.78936767578125
    }
}
